[
  {
    "fuente": "booking",
    "destino": "Manglaralto Ecuador",
    "nombre": "Tagualodge Hostel Manglaralto",
    "precio_raw": "US$110",
    "rating_raw": "Puntuación: 10\n10\nExcepcional\n48 comentarios",
    "checkin": "2026-07-19",
    "checkout": "2026-07-21",
    "fecha_extraccion": "2026-06-19T20:07:41.546943"
  },
  {
    "fuente": "booking",
    "destino": "Manglaralto Ecuador",
    "nombre": "Puerta Sol Inn",
    "precio_raw": "US$102",
    "rating_raw": "Puntuación: 8,7\n8,7\nFabuloso\n14 comentarios",
    "checkin": "2026-07-19",
    "checkout": "2026-07-21",
    "fecha_extraccion": "2026-06-19T20:07:41.598801"
  },
  {
    "fuente": "booking",
    "destino": "Manglaralto Ecuador",
    "nombre": "Hotel Milano Olon",
    "precio_raw": "US$120",
    "rating_raw": null,
    "checkin": "2026-07-19",
    "checkout": "2026-07-21",
    "fecha_extraccion": "2026-06-19T20:07:41.640387"
  },
  {
    "fuente": "booking",
    "destino": "Manglaralto Ecuador",
    "nombre": "Casa playa Manglaralto",
    "precio_raw": "US$56",
    "rating_raw": "Puntuación: 1,0\n1,0\nPuntuación\n1 comentario",
    "checkin": "2026-07-19",
    "checkout": "2026-07-21",
    "fecha_extraccion": "2026-06-19T20:07:41.683614"
  },
  {
    "fuente": "booking",
    "destino": "Manglaralto Ecuador",
    "nombre": "Mar Om",
    "precio_raw": "US$187",
    "rating_raw": "Puntuación: 10\n10\nExcepcional\n1 comentario",
    "checkin": "2026-07-19",
    "checkout": "2026-07-21",
    "fecha_extraccion": "2026-06-19T20:07:41.728499"
  },
  {
    "fuente": "booking",
    "destino": "Manglaralto Ecuador",
    "nombre": "Hotel Kundalini",
    "precio_raw": "US$78",
    "rating_raw": "Puntuación: 9,4\n9,4\nFantástico\n1.170 comentarios",
    "checkin": "2026-07-19",
    "checkout": "2026-07-21",
    "fecha_extraccion": "2026-06-19T20:07:41.782097"
  },
  {
    "fuente": "booking",
    "destino": "Manglaralto Ecuador",
    "nombre": "Hotel Sol y Playa Montañita",
    "precio_raw": "US$55",
    "rating_raw": "Puntuación: 8,0\n8,0\nMuy bien\n305 comentarios",
    "checkin": "2026-07-19",
    "checkout": "2026-07-21",
    "fecha_extraccion": "2026-06-19T20:07:41.842645"
  },
  {
    "fuente": "booking",
    "destino": "Manglaralto Ecuador",
    "nombre": "Casa del Sol",
    "precio_raw": "US$70",
    "rating_raw": "Puntuación: 9,3\n9,3\nFantástico\n320 comentarios",
    "checkin": "2026-07-19",
    "checkout": "2026-07-21",
    "fecha_extraccion": "2026-06-19T20:07:41.895763"
  },
  {
    "fuente": "booking",
    "destino": "Manglaralto Ecuador",
    "nombre": "Hotel Karukera",
    "precio_raw": "US$63",
    "rating_raw": "Puntuación: 7,9\n7,9\nBien\n95 comentarios",
    "checkin": "2026-07-19",
    "checkout": "2026-07-21",
    "fecha_extraccion": "2026-06-19T20:07:41.948119"
  },
  {
    "fuente": "booking",
    "destino": "Manglaralto Ecuador",
    "nombre": "ME Hotel & Villas - Montañita Estates",
    "precio_raw": "US$157",
    "rating_raw": "Puntuación: 8,1\n8,1\nMuy bien\n194 comentarios",
    "checkin": "2026-07-19",
    "checkout": "2026-07-21",
    "fecha_extraccion": "2026-06-19T20:07:42.002975"
  },
  {
    "fuente": "booking",
    "destino": "Manglaralto Ecuador",
    "nombre": "Hostal Mamacocha",
    "precio_raw": "US$29",
    "rating_raw": "Puntuación: 7,5\n7,5\nBien\n171 comentarios",
    "checkin": "2026-07-19",
    "checkout": "2026-07-21",
    "fecha_extraccion": "2026-06-19T20:07:42.049355"
  },
  {
    "fuente": "booking",
    "destino": "Manglaralto Ecuador",
    "nombre": "HiDDEN HOUSE",
    "precio_raw": "US$60",
    "rating_raw": "Puntuación: 7,9\n7,9\nBien\n9 comentarios",
    "checkin": "2026-07-19",
    "checkout": "2026-07-21",
    "fecha_extraccion": "2026-06-19T20:07:42.096216"
  },
  {
    "fuente": "booking",
    "destino": "Manglaralto Ecuador",
    "nombre": "La Gondola",
    "precio_raw": "US$74",
    "rating_raw": "Puntuación: 8,9\n8,9\nFabuloso\n173 comentarios",
    "checkin": "2026-07-19",
    "checkout": "2026-07-21",
    "fecha_extraccion": "2026-06-19T20:07:42.156949"
  },
  {
    "fuente": "booking",
    "destino": "Manglaralto Ecuador",
    "nombre": "Tiki Limbo",
    "precio_raw": "US$86",
    "rating_raw": "Puntuación: 8,1\n8,1\nMuy bien\n135 comentarios",
    "checkin": "2026-07-19",
    "checkout": "2026-07-21",
    "fecha_extraccion": "2026-06-19T20:07:42.223566"
  },
  {
    "fuente": "booking",
    "destino": "Manglaralto Ecuador",
    "nombre": "Hotel Sotavento",
    "precio_raw": "US$100",
    "rating_raw": "Puntuación: 8,7\n8,7\nFabuloso\n25 comentarios",
    "checkin": "2026-07-19",
    "checkout": "2026-07-21",
    "fecha_extraccion": "2026-06-19T20:07:42.303237"
  },
  {
    "fuente": "booking",
    "destino": "Manglaralto Ecuador",
    "nombre": "Hotel SoleMare",
    "precio_raw": "US$56",
    "rating_raw": "Puntuación: 9,2\n9,2\nFantástico\n120 comentarios",
    "checkin": "2026-07-19",
    "checkout": "2026-07-21",
    "fecha_extraccion": "2026-06-19T20:07:42.369889"
  },
  {
    "fuente": "booking",
    "destino": "Manglaralto Ecuador",
    "nombre": "Hostal Yaku Montañita",
    "precio_raw": "US$20",
    "rating_raw": "Puntuación: 8,8\n8,8\nFabuloso\n95 comentarios",
    "checkin": "2026-07-19",
    "checkout": "2026-07-21",
    "fecha_extraccion": "2026-06-19T20:07:42.426903"
  },
  {
    "fuente": "booking",
    "destino": "Manglaralto Ecuador",
    "nombre": "HANGA ROA HOTEL",
    "precio_raw": "US$105",
    "rating_raw": "Puntuación: 8,4\n8,4\nMuy bien\n264 comentarios",
    "checkin": "2026-07-19",
    "checkout": "2026-07-21",
    "fecha_extraccion": "2026-06-19T20:07:42.486266"
  },
  {
    "fuente": "booking",
    "destino": "Manglaralto Ecuador",
    "nombre": "My Little house Montanita",
    "precio_raw": "US$22",
    "rating_raw": "Puntuación: 8,2\n8,2\nMuy bien\n89 comentarios",
    "checkin": "2026-07-19",
    "checkout": "2026-07-21",
    "fecha_extraccion": "2026-06-19T20:07:42.543116"
  },
  {
    "fuente": "booking",
    "destino": "Manglaralto Ecuador",
    "nombre": "Kamala Surf & Backpacker Hostel",
    "precio_raw": "US$60",
    "rating_raw": "Puntuación: 8,7\n8,7\nFabuloso\n249 comentarios",
    "checkin": "2026-07-19",
    "checkout": "2026-07-21",
    "fecha_extraccion": "2026-06-19T20:07:42.590555"
  },
  {
    "fuente": "booking",
    "destino": "Manglaralto Ecuador",
    "nombre": "UFO Rooms",
    "precio_raw": "US$30",
    "rating_raw": "Puntuación: 7,6\n7,6\nBien\n117 comentarios",
    "checkin": "2026-07-19",
    "checkout": "2026-07-21",
    "fecha_extraccion": "2026-06-19T20:07:42.641724"
  },
  {
    "fuente": "booking",
    "destino": "Manglaralto Ecuador",
    "nombre": "Dharma Beach",
    "precio_raw": "US$180",
    "rating_raw": "Puntuación: 8,7\n8,7\nFabuloso\n99 comentarios",
    "checkin": "2026-07-19",
    "checkout": "2026-07-21",
    "fecha_extraccion": "2026-06-19T20:07:42.699096"
  },
  {
    "fuente": "booking",
    "destino": "Manglaralto Ecuador",
    "nombre": "Hostal Rosa Mística",
    "precio_raw": "US$110",
    "rating_raw": "Puntuación: 6,7\n6,7\nPuntuación\n3 comentarios",
    "checkin": "2026-07-19",
    "checkout": "2026-07-21",
    "fecha_extraccion": "2026-06-19T20:07:42.762338"
  },
  {
    "fuente": "booking",
    "destino": "Manglaralto Ecuador",
    "nombre": "Paradise Project Hostal",
    "precio_raw": "US$120",
    "rating_raw": "Puntuación: 7,2\n7,2\nBien\n64 comentarios",
    "checkin": "2026-07-19",
    "checkout": "2026-07-21",
    "fecha_extraccion": "2026-06-19T20:07:42.832823"
  },
  {
    "fuente": "booking",
    "destino": "Manglaralto Ecuador",
    "nombre": "Casa Del Merman at GayMontanita House",
    "precio_raw": "US$84",
    "rating_raw": "Puntuación: 9,4\n9,4\nFantástico\n138 comentarios",
    "checkin": "2026-07-19",
    "checkout": "2026-07-21",
    "fecha_extraccion": "2026-06-19T20:07:42.891291"
  }
]